{
    "format_version": "1.10.0",
    "minecraft:client_entity": {
        "description": {
            "identifier": "cobblemon:0071_victreebel",
            "materials": {
                "default": "entity_alphatest"
            },
            "textures": {
                "default": "textures/entity/0071_victreebel/victreebel"
            },
            "geometry": {
                "default": "geometry.victreebel"
            },
            "scripts": {
                "animate": [
                    "pose"
                ]
            },
            "animations": {
                "pose": "controller.animation.victreebel.pose",
                "ground_idle": "animation.victreebel.ground_idle"
            },
            "render_controllers": [
                "controller.render.agent"
            ],
            "spawn_egg": {
                "texture": "0071_victreebel_spawn_egg"
            }
        }
    }
}