{
    "format_version": "1.10.0",
    "minecraft:client_entity": {
        "description": {
            "identifier": "cobblemon:0095_onix",
            "materials": {
                "default": "entity_alphatest"
            },
            "textures": {
                "default": "textures/entity/0095_onix/onix"
            },
            "geometry": {
                "default": "geometry.onix"
            },
            "scripts": {
                "animate": [
                    "pose"
                ]
            },
            "animations": {
                "pose": "controller.animation.onix.pose",
                "ground_idle": "animation.onix.ground_idle",
                "ground_walk": "animation.onix.ground_walk",
                "battle_idle": "animation.onix.battle_idle",
                "boulder_rotation": "animation.onix.boulder_rotation",
                "slow_boulder_rotation": "animation.onix.slow_boulder_rotation",
                "cry": "animation.onix.cry",
                "blink": "animation.onix.blink",
                "sleep": "animation.onix.sleep",
                "faint": "animation.onix.faint",
                "summary_idle": "animation.onix.summary_idle"
            },
            "render_controllers": [
                "controller.render.agent"
            ],
            "spawn_egg": {
                "texture": "0095_onix_spawn_egg"
            }
        }
    }
}