{
    "format_version": "1.10.0",
    "minecraft:client_entity": {
        "description": {
            "identifier": "cobblemon:0100_voltorb",
            "materials": {
                "default": "entity_alphatest"
            },
            "textures": {
                "default": "textures/entity/0100_voltorb/voltorb"
            },
            "geometry": {
                "default": "geometry.voltorb"
            },
            "scripts": {
                "animate": [
                    "pose"
                ]
            },
            "animations": {
                "faint": "animation.voltorb.faint",
                "ground_idle": "animation.voltorb.ground_idle",
                "ground_walk": "animation.voltorb.ground_walk",
                "sleep": "animation.voltorb.sleep",
                "pose": "controller.animation.voltorb.pose"
            },
            "render_controllers": [
                "controller.render.agent"
            ],
            "spawn_egg": {
                "texture": "0100_voltorb_spawn_egg"
            }
        }
    }
}