{
    "format_version": "1.10.0",
    "minecraft:client_entity": {
        "description": {
            "identifier": "cobblemon:0158_totodile",
            "materials": {
                "default": "entity_alphatest"
            },
            "textures": {
                "default": "textures/entity/0158_totodile/totodile"
            },
            "geometry": {
                "default": "geometry.totodile"
            },
            "scripts": {
                "animate": [
                    "pose"
                ]
            },
            "animations": {
                "faint": "animation.totodile.faint",
                "ground_idle": "animation.totodile.ground_idle",
                "ground_walk": "animation.totodile.ground_walk",
                "sleep": "animation.totodile.sleep",
                "pose": "controller.animation.totodile.pose"
            },
            "render_controllers": [
                "controller.render.agent"
            ],
            "spawn_egg": {
                "texture": "0158_totodile_spawn_egg"
            }
        }
    }
}