{
    "format_version": "1.10.0",
    "minecraft:client_entity": {
        "description": {
            "identifier": "cobblemon:0464_rhyperior",
            "materials": {
                "default": "entity_alphatest"
            },
            "textures": {
                "default": "textures/entity/0464_rhyperior/rhyperior"
            },
            "geometry": {
                "default": "geometry.rhyperior"
            },
            "scripts": {
                "animate": [
                    "pose"
                ]
            },
            "animations": {
                "faint": "animation.rhyperior.faint",
                "ground_idle": "animation.rhyperior.ground_idle",
                "ground_walk": "animation.rhyperior.ground_walk",
                "sleep": "animation.rhyperior.sleep",
                "pose": "controller.animation.rhyperior.pose"
            },
            "render_controllers": [
                "controller.render.agent"
            ],
            "spawn_egg": {
                "texture": "0464_rhyperior_spawn_egg"
            }
        }
    }
}