{
    "format_version": "1.10.0",
    "minecraft:client_entity": {
        "description": {
            "identifier": "cobblemon:0760_bewear",
            "materials": {
                "default": "entity_alphatest"
            },
            "textures": {
                "default": "textures/entity/0760_bewear/bewear"
            },
            "geometry": {
                "default": "geometry.bewear"
            },
            "scripts": {
                "animate": [
                    "pose"
                ]
            },
            "animations": {
                "pose": "controller.animation.bewear.pose",
                "blink": "animation.bewear.blink",
                "ground_idle": "animation.bewear.ground_idle",
                "ground_walk": "animation.bewear.ground_walk",
                "ground_run": "animation.bewear.ground_run",
                "battle_idle": "animation.bewear.battle_idle",
                "faint": "animation.bewear.faint",
                "sleep": "animation.bewear.sleep",
                "cry": "animation.bewear.cry"
            },
            "render_controllers": [
                "controller.render.agent"
            ],
            "spawn_egg": {
                "texture": "0760_bewear_spawn_egg"
            }
        }
    }
}